wcpan/queue/__init__.py
wcpan/queue/py.typed
wcpan_queue-7.2.1.dist-info/LICENSE.txt
wcpan_queue-7.2.1.dist-info/METADATA
wcpan_queue-7.2.1.dist-info/WHEEL
wcpan_queue-7.2.1.dist-info/RECORD
