Metadata-Version: 2.1
Name: wcpan-queue
Version: 7.2.1
Summary: An utility for asyncio.Queue.
Home-page: https://github.com/legnaleurc/wcpan.queue
License: MIT
Author: Wei-Cheng Pan
Author-email: legnaleurc@gmail.com
Requires-Python: >=3.12,<4.0
Classifier: Development Status :: 3 - Alpha
Classifier: Framework :: AsyncIO
Classifier: Intended Audience :: Developers
Classifier: License :: OSI Approved :: MIT License
Classifier: Operating System :: OS Independent
Classifier: Programming Language :: Python :: 3
Classifier: Programming Language :: Python :: 3.12
Classifier: Topic :: Software Development :: Libraries
Classifier: Typing :: Typed
Project-URL: Repository, https://github.com/legnaleurc/wcpan.queue
